mdit_plain_tts/__init__.py
mdit_plain_tts/renderer.py
mdit_plain_tts-1.0.2.dist-info/LICENSE
mdit_plain_tts-1.0.2.dist-info/METADATA
mdit_plain_tts-1.0.2.dist-info/WHEEL
mdit_plain_tts-1.0.2.dist-info/top_level.txt
mdit_plain_tts-1.0.2.dist-info/RECORD
